{
    "products": [
        {
            "id": 2,
            "price": 30000,
            "type": "Com",
            "name": "Com Suon",
            "imageUrl": "https://s3.amazonaws.com/demouploadimage/sushi.jpg",
            "recipe": {
                "direction": "blah com suon",
                "type": "Not Charge",
                "ingredients": []
            }
        },
        {
            "id": 13,
            "price": 15000,
            "type": "Do An",
            "name": "Banh Cuon",
            "imageUrl": "https://s3.amazonaws.com/demouploadimage/sushi.jpg",
            "recipe": {
                "direction": "blah Banh Cuon",
                "type": "Not Charge",
                "ingredients": [
                    {
                        "detail": "1 Banh Cuon"
                    },
                    {
                        "detail": "ABC"
                    },
                    {
                        "detail": "XYZ"
                    }
                ]
            }
        },
        {
            "id": 4,
            "price": 15000,
            "type": "Drink",
            "name": "Tra sua",
            "imageUrl": "https://s3.amazonaws.com/demouploadimage/sushi.jpg",
            "recipe": {
                "direction": "blah tra sua",
                "type": "Not Charge",
                "ingredients": []
            }
        },
        {
            "id": 1,
            "price": 30000,
            "type": "Com",
            "name": "Com Ga",
            "imageUrl": "https://s3.amazonaws.com/demouploadimage/sushi.jpg",
            "recipe": {
                "direction": "blah com ga",
                "type": "Not Charge",
                "ingredients": [
                    {
                        "detail": "1 con ga"
                    },
                    {
                        "detail": "5g gao"
                    },
                    {
                        "detail": "rau"
                    }
                ]
            }
        },
        {
            "id": 3,
            "price": 30000,
            "type": "Com",
            "name": "Com Chay",
            "imageUrl": "https://s3.amazonaws.com/demouploadimage/sushi.jpg",
            "recipe": {
                "direction": "blah com chay",
                "type": "Not Charge",
                "ingredients": []
            }
        },
        {
            "id": 14,
            "price": 10000,
            "type": "Do An",
            "name": "Banh Canh",
            "imageUrl": "https://s3.amazonaws.com/demouploadimage/sushi.jpg",
            "recipe": {
                "direction": "blah Banh Canh",
                "type": "Not Charge",
                "ingredients": [
                    {
                        "detail": "2 Banh Canh"
                    },
                    {
                        "detail": "DEF"
                    },
                    {
                        "detail": "ABC"
                    }
                ]
            }
        }
    ]
}
